qsimov/__init__.py
qsimov/qsimov.py
qsimov/connectors/__init__.py
qsimov/connectors/drewom.py
qsimov/connectors/forestapi.py
qsimov/connectors/parser.py
qsimov/connectors/qsimovapi.py
qsimov/cores/__init__.py
qsimov/cores/bdoki.py
qsimov/samples/__init__.py
qsimov/samples/djcircuit.py
qsimov/samples/fourier.py
qsimov/samples/state_gate.py
qsimov/structures/__init__.py
qsimov/structures/funmatrix.py
qsimov/structures/qbase.py
qsimov/structures/qcircuit.py
qsimov/structures/qdesign.py
qsimov/structures/qgate.py
qsimov/structures/qregistry.py
qsimov/structures/qstructure.py
qsimov/structures/qsystem.py
qsimov/structures/simple_gate.py
qsimov/utils/__init__.py
qsimov/utils/bloch.py
qsimov-5.1.3.dist-info/LICENSE.md
qsimov-5.1.3.dist-info/METADATA
qsimov-5.1.3.dist-info/WHEEL
qsimov-5.1.3.dist-info/top_level.txt
qsimov-5.1.3.dist-info/RECORD
