Metadata-Version: 2.1
Name: qsimov
Version: 5.1.3
Summary: QSimov: A Quantum Computing Toolkit
Author-email: Hernán Indíbil de la Cruz Calvo <indikalesken@hotmail.com>
License: 
Project-URL: Homepage, https://forum.clanjhoo.com
Project-URL: Documentation, https://github.com/Mowstyl/QSimov/wiki
Project-URL: Repository, https://github.com/Mowstyl/QSimov.git
Project-URL: Issues, https://github.com/Mowstyl/QSimov/issues
Project-URL: Changelog, https://github.com/Mowstyl/QSimov/commits
Keywords: quantum
Classifier: License :: OSI Approved :: GNU General Public License v3 or later (GPLv3+)
Classifier: Operating System :: OS Independent
Classifier: Programming Language :: Python :: 3
Classifier: Programming Language :: Python :: 3.8
Classifier: Programming Language :: Python :: 3.9
Classifier: Programming Language :: Python :: 3.10
Classifier: Programming Language :: Python :: 3.11
Classifier: Programming Language :: Python :: 3.12
Classifier: Topic :: Scientific/Engineering :: Mathematics
Classifier: Topic :: Scientific/Engineering :: Physics
Requires-Python: >=3.8
License-File: LICENSE.md
Requires-Dist: numpy >=1.21
Requires-Dist: matplotlib >=3.5.1
Requires-Dist: doki-Mowstyl >=1.5.2
Requires-Dist: sympy
